fastapi_esql/__init__.py
fastapi_esql/const/__init__.py
fastapi_esql/const/error.py
fastapi_esql/orm/__init__.py
fastapi_esql/orm/base_app.py
fastapi_esql/orm/base_manager.py
fastapi_esql/orm/base_model.py
fastapi_esql/utils/__init__.py
fastapi_esql/utils/converter.py
fastapi_esql/utils/cursor_handler.py
fastapi_esql/utils/decorator.py
fastapi_esql/utils/metaclass.py
fastapi_esql/utils/sqlizer.py
fastapi_efficient_sql-0.0.15.dist-info/LICENSE
fastapi_efficient_sql-0.0.15.dist-info/METADATA
fastapi_efficient_sql-0.0.15.dist-info/WHEEL
fastapi_efficient_sql-0.0.15.dist-info/RECORD
