Metadata-Version: 2.1
Name: fastapi-efficient-sql
Version: 0.0.15
Summary: Generate bulk DML SQL and execute them based on Tortoise ORM and mysql8.0+, and integrated with FastAPI.
Home-page: https://github.com/NightMarcher/fastapi-efficient-sql
License: MIT
Keywords: sql,fastapi,tortoise-orm,mysql8,bulk-operation
Author: BryanLee
Author-email: bryanlee@126.com
Requires-Python: >=3.7,<4.0
Classifier: License :: OSI Approved :: MIT License
Classifier: Programming Language :: Python :: 3
Classifier: Programming Language :: Python :: 3.7
Classifier: Programming Language :: Python :: 3.8
Classifier: Programming Language :: Python :: 3.9
Classifier: Programming Language :: Python :: 3.10
Classifier: Programming Language :: Python :: 3.11
Classifier: Programming Language :: Python :: 3
Classifier: Programming Language :: Python :: 3.7
